<Map background-color="white">
    <Parameters>
        <Parameter name="sizes">256,256</Parameter>
    </Parameters>

    <Style name="polygon">
        <Rule>
            <PolygonSymbolizer
                fill="#408090"
                />
        </Rule>
    </Style>

    <Layer name="polygon" comp-op="grain-merge-over">
        <StyleName>polygon</StyleName>
        <Datasource>
            <Parameter name="type">csv</Parameter>
            <Parameter name="inline">
                wkt
                "POLYGON((1 0, 0 -1, -1 0, 0 1, 1 0))"
            </Parameter>
        </Datasource>
    </Layer>
</Map>
